{"def":[[{"FATHER":"MiscGroups.List","NAME_DEF":" Id","ID":"1","TYPE":" UInt","VALUE":" 0"},{"FATHER":"MiscGroups.List","NAME_DEF":" Description","ID":"2","TYPE":" String","LENGTH_DEF":"25","VALUE":""},{"FATHER":"MiscGroups.List","NAME_DEF":" MaxMiscGroupReceiptAmount","ID":"3","TYPE":" Array","TYPE_FIELDS":"ULong","LENGTH":"3","VALUES":[{"NAME":" MaxMiscGroupReceiptAmount_0","VALUE":" -plus--plus--plus-","DELIMITER":"0"},{"NAME":" MaxMiscGroupReceiptAmount_1","VALUE":" -plus--plus--plus-","DELIMITER":"0"},{"NAME":" MaxMiscGroupReceiptAmount_2","VALUE":" -plus--plus--plus-","DELIMITER":"0"}]},{"FATHER":"MiscGroups.List","NAME_DEF":" MaxMiscGroupPayoutAmount","ID":"4","TYPE":" Array","TYPE_FIELDS":"ULong","LENGTH":"3","VALUES":[{"NAME":" MaxMiscGroupPayoutAmount_0","VALUE":" 5000","DELIMITER":"0"},{"NAME":" MaxMiscGroupPayoutAmount_1","VALUE":" 10000","DELIMITER":"0"},{"NAME":" MaxMiscGroupPayoutAmount_2","VALUE":" 15000","DELIMITER":"0"}]},{"FATHER":"MiscGroups.List","NAME_DEF":" MinimumGroupMiscPayoutAmount","ID":"5","TYPE":" Array","TYPE_FIELDS":"ULong","LENGTH":"3","VALUES":[{"NAME":" MinimumGroupMiscPayoutAmount_0","VALUE":" 150","DELIMITER":"0"},{"NAME":" MinimumGroupMiscPayoutAmount_1","VALUE":" 100","DELIMITER":"0"},{"NAME":" MinimumGroupMiscPayoutAmount_2","VALUE":" 50","DELIMITER":"0"}]},{"FATHER":"MiscGroups.List","NAME_DEF":" MinimumGroupMiscReceiptAmount","ID":"6","TYPE":" Array","TYPE_FIELDS":"ULong","LENGTH":"3","VALUES":[{"NAME":" MinimumGroupMiscReceiptAmount_0","VALUE":" 150","DELIMITER":"0"},{"NAME":" MinimumGroupMiscReceiptAmount_1","VALUE":" 100","DELIMITER":"0"},{"NAME":" MinimumGroupMiscReceiptAmount_2","VALUE":" 50","DELIMITER":"0"}]},{"FATHER":"MiscGroups.List","NAME_DEF":" MiscGroupPayoutQuantity","ID":"7","TYPE":" Array","TYPE_FIELDS":"UInt","LENGTH":"3","VALUES":[{"NAME":" MiscGroupPayoutQuantity_0","VALUE":" -plus--plus--plus-","DELIMITER":"0"},{"NAME":" MiscGroupPayoutQuantity_1","VALUE":" -plus--plus--plus-","DELIMITER":"0"},{"NAME":" MiscGroupPayoutQuantity_2","VALUE":" -plus--plus--plus-","DELIMITER":"0"}]},{"FATHER":"MiscGroups.List","NAME_DEF":" MiscGroupReceiptQuantity","ID":"8","TYPE":" Array","TYPE_FIELDS":"UInt","LENGTH":"3","VALUES":[{"NAME":" MiscGroupReceiptQuantity_0","VALUE":" -plus--plus--plus-","DELIMITER":"0"},{"NAME":" MiscGroupReceiptQuantity_1","VALUE":" -plus--plus--plus-","DELIMITER":"0"},{"NAME":" MiscGroupReceiptQuantity_2","VALUE":" -plus--plus--plus-","DELIMITER":"0"}]},{"FATHER":"MiscGroups.List","NAME_DEF":" MiscAccount","ID":"9","TYPE":" Array","TYPE_FIELDS":"UInt","LENGTH":"20","VALUES":[{"NAME":" MiscAccount_0","VALUE":" -plus--plus--plus-","DELIMITER":"0"},{"NAME":" MiscAccount_1","VALUE":" -plus--plus--plus-","DELIMITER":"0"},{"NAME":" MiscAccount_2","VALUE":" -plus--plus--plus-","DELIMITER":"0"},{"NAME":" MiscAccount_3","VALUE":" -plus--plus--plus-","DELIMITER":"0"},{"NAME":" MiscAccount_4","VALUE":" -plus--plus--plus-","DELIMITER":"0"},{"NAME":" MiscAccount_5","VALUE":" -plus--plus--plus-","DELIMITER":"0"},{"NAME":" MiscAccount_6","VALUE":" -plus--plus--plus-","DELIMITER":"0"},{"NAME":" MiscAccount_7","VALUE":" -plus--plus--plus-","DELIMITER":"0"},{"NAME":" MiscAccount_8","VALUE":" -plus--plus--plus-","DELIMITER":"0"},{"NAME":" MiscAccount_9","VALUE":" -plus--plus--plus-","DELIMITER":"0"},{"NAME":" MiscAccount_10","VALUE":" -plus--plus--plus-","DELIMITER":"0"},{"NAME":" MiscAccount_11","VALUE":" -plus--plus--plus-","DELIMITER":"0"},{"NAME":" MiscAccount_12","VALUE":" -plus--plus--plus-","DELIMITER":"0"},{"NAME":" MiscAccount_13","VALUE":" -plus--plus--plus-","DELIMITER":"0"},{"NAME":" MiscAccount_14","VALUE":" -plus--plus--plus-","DELIMITER":"0"},{"NAME":" MiscAccount_15","VALUE":" -plus--plus--plus-","DELIMITER":"0"},{"NAME":" MiscAccount_16","VALUE":" -plus--plus--plus-","DELIMITER":"0"},{"NAME":" MiscAccount_17","VALUE":" -plus--plus--plus-","DELIMITER":"0"},{"NAME":" MiscAccount_18","VALUE":" -plus--plus--plus-","DELIMITER":"0"},{"NAME":" MiscAccount_19","VALUE":" -plus--plus--plus-","DELIMITER":"0"}]},{"FATHER":"MiscGroups.List","NAME_DEF":" DeleteFlag","ID":"99","TYPE":" Boolean","VALUE":" 0"}]],"fields":[[{"FATHER":"MiscGroups.List.0","NAME_FIELD":" Description","VALUE":" -cdoble-Grupo cuenta varios 1-cdoble-"},{"FATHER":"MiscGroups.List.0","NAME_FIELD":" MaxMiscGroupReceiptAmount","VALUES":[{"NAME":" MaxMiscGroupReceiptAmount_0","VALUE":" -plus--plus--plus-","DELIMITER":"0"},{"NAME":" MaxMiscGroupReceiptAmount_1","VALUE":" -plus--plus--plus-","DELIMITER":"0"},{"NAME":" MaxMiscGroupReceiptAmount_2","VALUE":" -plus--plus--plus-","DELIMITER":"0"}]},{"FATHER":"MiscGroups.List.0","NAME_FIELD":" MaxMiscGroupPayoutAmount","VALUES":[{"NAME":" MaxMiscGroupPayoutAmount_0","VALUE":" 5000","DELIMITER":"0"},{"NAME":" MaxMiscGroupPayoutAmount_1","VALUE":" 10000","DELIMITER":"0"},{"NAME":" MaxMiscGroupPayoutAmount_2","VALUE":" 15000","DELIMITER":"0"}]},{"FATHER":"MiscGroups.List.0","NAME_FIELD":" MinimumGroupMiscPayoutAmount","VALUES":[{"NAME":" MinimumGroupMiscPayoutAmount_0","VALUE":" 150","DELIMITER":"0"},{"NAME":" MinimumGroupMiscPayoutAmount_1","VALUE":" 100","DELIMITER":"0"},{"NAME":" MinimumGroupMiscPayoutAmount_2","VALUE":" 50","DELIMITER":"0"}]},{"FATHER":"MiscGroups.List.0","NAME_FIELD":" MinimumGroupMiscReceiptAmount","VALUES":[{"NAME":" MinimumGroupMiscReceiptAmount_0","VALUE":" 150","DELIMITER":"0"},{"NAME":" MinimumGroupMiscReceiptAmount_1","VALUE":" 100","DELIMITER":"0"},{"NAME":" MinimumGroupMiscReceiptAmount_2","VALUE":" 50","DELIMITER":"0"}]},{"FATHER":"MiscGroups.List.0","NAME_FIELD":" MiscGroupPayoutQuantity","VALUES":[{"NAME":" MiscGroupPayoutQuantity_0","VALUE":" -plus--plus--plus-","DELIMITER":"0"},{"NAME":" MiscGroupPayoutQuantity_1","VALUE":" -plus--plus--plus-","DELIMITER":"0"},{"NAME":" MiscGroupPayoutQuantity_2","VALUE":" -plus--plus--plus-","DELIMITER":"0"}]},{"FATHER":"MiscGroups.List.0","NAME_FIELD":" MiscGroupReceiptQuantity","VALUES":[{"NAME":" MiscGroupReceiptQuantity_0","VALUE":" -plus--plus--plus-","DELIMITER":"0"},{"NAME":" MiscGroupReceiptQuantity_1","VALUE":" -plus--plus--plus-","DELIMITER":"0"},{"NAME":" MiscGroupReceiptQuantity_2","VALUE":" -plus--plus--plus-","DELIMITER":"0"}]},{"FATHER":"MiscGroups.List.0","NAME_FIELD":" MiscAccount","VALUES":[{"NAME":" MiscAccount_0","VALUE":" -plus--plus--plus-","DELIMITER":"0"},{"NAME":" MiscAccount_1","VALUE":" -plus--plus--plus-","DELIMITER":"0"},{"NAME":" MiscAccount_2","VALUE":" -plus--plus--plus-","DELIMITER":"0"},{"NAME":" MiscAccount_3","VALUE":" -plus--plus--plus-","DELIMITER":"0"},{"NAME":" MiscAccount_4","VALUE":" -plus--plus--plus-","DELIMITER":"0"},{"NAME":" MiscAccount_5","VALUE":" -plus--plus--plus-","DELIMITER":"0"},{"NAME":" MiscAccount_6","VALUE":" -plus--plus--plus-","DELIMITER":"0"},{"NAME":" MiscAccount_7","VALUE":" -plus--plus--plus-","DELIMITER":"0"},{"NAME":" MiscAccount_8","VALUE":" -plus--plus--plus-","DELIMITER":"0"},{"NAME":" MiscAccount_9","VALUE":" -plus--plus--plus-","DELIMITER":"0"},{"NAME":" MiscAccount_10","VALUE":" -plus--plus--plus-","DELIMITER":"0"},{"NAME":" MiscAccount_11","VALUE":" -plus--plus--plus-","DELIMITER":"0"},{"NAME":" MiscAccount_12","VALUE":" -plus--plus--plus-","DELIMITER":"0"},{"NAME":" MiscAccount_13","VALUE":" -plus--plus--plus-","DELIMITER":"0"},{"NAME":" MiscAccount_14","VALUE":" -plus--plus--plus-","DELIMITER":"0"},{"NAME":" MiscAccount_15","VALUE":" -plus--plus--plus-","DELIMITER":"0"},{"NAME":" MiscAccount_16","VALUE":" -plus--plus--plus-","DELIMITER":"0"},{"NAME":" MiscAccount_17","VALUE":" -plus--plus--plus-","DELIMITER":"0"},{"NAME":" MiscAccount_18","VALUE":" -plus--plus--plus-","DELIMITER":"0"},{"NAME":" MiscAccount_19","VALUE":" -plus--plus--plus-","DELIMITER":"0"}]},{"FATHER":"MiscGroups.List.0","NAME_FIELD":" DeleteFlag","VALUE":" 0"}]]}