{"def":[[{"FATHER":"AutoLoans.List","NAME_DEF":" Id","ID":"1","TYPE":" UInt","VALUE":""},{"FATHER":"AutoLoans.List","NAME_DEF":" Entry1","ID":"11","TYPE":" Array","TYPE_FIELDS":"ULong","LENGTH":"4","VALUES":[{"NAME":" Entry1_0","VALUE":" 0","DELIMITER":"0"},{"NAME":" Entry1_1","VALUE":" 0","DELIMITER":"0"},{"NAME":" Entry1_2","VALUE":" 0","DELIMITER":"0"},{"NAME":" Entry1_3","VALUE":" 0","DELIMITER":"0"}]},{"FATHER":"AutoLoans.List","NAME_DEF":" Entry2","ID":"12","TYPE":" Array","TYPE_FIELDS":"ULong","LENGTH":"4","VALUES":[{"NAME":" Entry2_0","VALUE":" 0","DELIMITER":"0"},{"NAME":" Entry2_1","VALUE":" 0","DELIMITER":"0"},{"NAME":" Entry2_2","VALUE":" 0","DELIMITER":"0"},{"NAME":" Entry2_3","VALUE":" 0","DELIMITER":"0"}]},{"FATHER":"AutoLoans.List","NAME_DEF":" Entry3","ID":"13","TYPE":" Array","TYPE_FIELDS":"ULong","LENGTH":"4","VALUES":[{"NAME":" Entry3_0","VALUE":" 0","DELIMITER":"0"},{"NAME":" Entry3_1","VALUE":" 0","DELIMITER":"0"},{"NAME":" Entry3_2","VALUE":" 0","DELIMITER":"0"},{"NAME":" Entry3_3","VALUE":" 0","DELIMITER":"0"}]},{"FATHER":"AutoLoans.List","NAME_DEF":" Entry4","ID":"14","TYPE":" Array","TYPE_FIELDS":"ULong","LENGTH":"4","VALUES":[{"NAME":" Entry4_0","VALUE":" 0","DELIMITER":"0"},{"NAME":" Entry4_1","VALUE":" 0","DELIMITER":"0"},{"NAME":" Entry4_2","VALUE":" 0","DELIMITER":"0"},{"NAME":" Entry4_3","VALUE":" 0","DELIMITER":"0"}]},{"FATHER":"AutoLoans.List","NAME_DEF":" Entry5","ID":"15","TYPE":" Array","TYPE_FIELDS":"ULong","LENGTH":"4","VALUES":[{"NAME":" Entry5_0","VALUE":" 0","DELIMITER":"0"},{"NAME":" Entry5_1","VALUE":" 0","DELIMITER":"0"},{"NAME":" Entry5_2","VALUE":" 0","DELIMITER":"0"},{"NAME":" Entry5_3","VALUE":" 0","DELIMITER":"0"}]},{"FATHER":"AutoLoans.List","NAME_DEF":" Entry6","ID":"16","TYPE":" Array","TYPE_FIELDS":"ULong","LENGTH":"4","VALUES":[{"NAME":" Entry6_0","VALUE":" 0","DELIMITER":"0"},{"NAME":" Entry6_1","VALUE":" 0","DELIMITER":"0"},{"NAME":" Entry6_2","VALUE":" 0","DELIMITER":"0"},{"NAME":" Entry6_3","VALUE":" 0","DELIMITER":"0"}]},{"FATHER":"AutoLoans.List","NAME_DEF":" Entry7","ID":"17","TYPE":" Array","TYPE_FIELDS":"ULong","LENGTH":"4","VALUES":[{"NAME":" Entry7_0","VALUE":" 0","DELIMITER":"0"},{"NAME":" Entry7_1","VALUE":" 0","DELIMITER":"0"},{"NAME":" Entry7_2","VALUE":" 0","DELIMITER":"0"},{"NAME":" Entry7_3","VALUE":" 0","DELIMITER":"0"}]},{"FATHER":"AutoLoans.List","NAME_DEF":" Entry8","ID":"18","TYPE":" Array","TYPE_FIELDS":"ULong","LENGTH":"4","VALUES":[{"NAME":" Entry8_0","VALUE":" 0","DELIMITER":"0"},{"NAME":" Entry8_1","VALUE":" 0","DELIMITER":"0"},{"NAME":" Entry8_2","VALUE":" 0","DELIMITER":"0"},{"NAME":" Entry8_3","VALUE":" 0","DELIMITER":"0"}]},{"FATHER":"AutoLoans.List","NAME_DEF":" Entry9","ID":"19","TYPE":" Array","TYPE_FIELDS":"ULong","LENGTH":"4","VALUES":[{"NAME":" Entry9_0","VALUE":" 0","DELIMITER":"0"},{"NAME":" Entry9_1","VALUE":" 0","DELIMITER":"0"},{"NAME":" Entry9_2","VALUE":" 0","DELIMITER":"0"},{"NAME":" Entry9_3","VALUE":" 0","DELIMITER":"0"}]},{"FATHER":"AutoLoans.List","NAME_DEF":" Entry10","ID":"20","TYPE":" Array","TYPE_FIELDS":"ULong","LENGTH":"4","VALUES":[{"NAME":" Entry10_0","VALUE":" 0","DELIMITER":"0"},{"NAME":" Entry10_1","VALUE":" 0","DELIMITER":"0"},{"NAME":" Entry10_2","VALUE":" 0","DELIMITER":"0"},{"NAME":" Entry10_3","VALUE":" 0","DELIMITER":"0"}]},{"FATHER":"AutoLoans.List","NAME_DEF":" DeleteFlag","ID":"99","TYPE":" Boolean","VALUE":" 0"}]],"fields":[[{"FATHER":"AutoLoans.List.0","NAME_FIELD":" Entry1","VALUES":[{"NAME":" Entry1_0","VALUE":" 1","DELIMITER":"0"},{"NAME":" Entry1_1","VALUE":" 1","DELIMITER":"0"},{"NAME":" Entry1_2","VALUE":" 5000","DELIMITER":"0"},{"NAME":" Entry1_3","VALUE":" 0","DELIMITER":"0"}]},{"FATHER":"AutoLoans.List.0","NAME_FIELD":" Entry2","VALUES":[{"NAME":" Entry2_0","VALUE":" 0","DELIMITER":"0"},{"NAME":" Entry2_1","VALUE":" 0","DELIMITER":"0"},{"NAME":" Entry2_2","VALUE":" 0","DELIMITER":"0"},{"NAME":" Entry2_3","VALUE":" 0","DELIMITER":"0"}]},{"FATHER":"AutoLoans.List.0","NAME_FIELD":" Entry3","VALUES":[{"NAME":" Entry3_0","VALUE":" 0","DELIMITER":"0"},{"NAME":" Entry3_1","VALUE":" 0","DELIMITER":"0"},{"NAME":" Entry3_2","VALUE":" 0","DELIMITER":"0"},{"NAME":" Entry3_3","VALUE":" 0","DELIMITER":"0"}]},{"FATHER":"AutoLoans.List.0","NAME_FIELD":" Entry4","VALUES":[{"NAME":" Entry4_0","VALUE":" 0","DELIMITER":"0"},{"NAME":" Entry4_1","VALUE":" 0","DELIMITER":"0"},{"NAME":" Entry4_2","VALUE":" 0","DELIMITER":"0"},{"NAME":" Entry4_3","VALUE":" 0","DELIMITER":"0"}]},{"FATHER":"AutoLoans.List.0","NAME_FIELD":" Entry5","VALUES":[{"NAME":" Entry5_0","VALUE":" 0","DELIMITER":"0"},{"NAME":" Entry5_1","VALUE":" 0","DELIMITER":"0"},{"NAME":" Entry5_2","VALUE":" 0","DELIMITER":"0"},{"NAME":" Entry5_3","VALUE":" 0","DELIMITER":"0"}]},{"FATHER":"AutoLoans.List.0","NAME_FIELD":" Entry6","VALUES":[{"NAME":" Entry6_0","VALUE":" 0","DELIMITER":"0"},{"NAME":" Entry6_1","VALUE":" 0","DELIMITER":"0"},{"NAME":" Entry6_2","VALUE":" 0","DELIMITER":"0"},{"NAME":" Entry6_3","VALUE":" 0","DELIMITER":"0"}]},{"FATHER":"AutoLoans.List.0","NAME_FIELD":" Entry7","VALUES":[{"NAME":" Entry7_0","VALUE":" 0","DELIMITER":"0"},{"NAME":" Entry7_1","VALUE":" 0","DELIMITER":"0"},{"NAME":" Entry7_2","VALUE":" 0","DELIMITER":"0"},{"NAME":" Entry7_3","VALUE":" 0","DELIMITER":"0"}]},{"FATHER":"AutoLoans.List.0","NAME_FIELD":" Entry8","VALUES":[{"NAME":" Entry8_0","VALUE":" 0","DELIMITER":"0"},{"NAME":" Entry8_1","VALUE":" 0","DELIMITER":"0"},{"NAME":" Entry8_2","VALUE":" 0","DELIMITER":"0"},{"NAME":" Entry8_3","VALUE":" 0","DELIMITER":"0"}]},{"FATHER":"AutoLoans.List.0","NAME_FIELD":" Entry9","VALUES":[{"NAME":" Entry9_0","VALUE":" 0","DELIMITER":"0"},{"NAME":" Entry9_1","VALUE":" 0","DELIMITER":"0"},{"NAME":" Entry9_2","VALUE":" 0","DELIMITER":"0"},{"NAME":" Entry9_3","VALUE":" 0","DELIMITER":"0"}]},{"FATHER":"AutoLoans.List.0","NAME_FIELD":" Entry10","VALUES":[{"NAME":" Entry10_0","VALUE":" 0","DELIMITER":"0"},{"NAME":" Entry10_1","VALUE":" 0","DELIMITER":"0"},{"NAME":" Entry10_2","VALUE":" 0","DELIMITER":"0"},{"NAME":" Entry10_3","VALUE":" 0","DELIMITER":"0"}]},{"FATHER":"AutoLoans.List.0","NAME_FIELD":" DeleteFlag","VALUE":" 0"}]]}