<Transaction TrainingModeFlag="false" OfflineFlag="false" CancelFlag="false" VoidedFlag="false">
  <OperatorID>0952317048</OperatorID>
  <WorkstationID>0005</WorkstationID>
  <RetailStoreID>065</RetailStoreID>
  <BusinessDayDate>2016-06-09</BusinessDayDate>
  <SequenceNumber>15</SequenceNumber>
  <BeginDateTime>2016-06-09T12:32:16</BeginDateTime>
  <EndDateTime>2016-06-09T12:44:00</EndDateTime>
  <RetailTransaction>
    <RingElapsedTime>692</RingElapsedTime>
    <TenderElapsedTime>12</TenderElapsedTime>
    <IdleElapsedTime>371</IdleElapsedTime>
    <LockElapsedTime>259</LockElapsedTime>
    <ItemCount>9.0</ItemCount>
    <LineItemsScannedCount>0.0</LineItemsScannedCount>
    <lineItemsScannedPercent>0.0</lineItemsScannedPercent>
    <LineItemsKeyedCount>9.0</LineItemsKeyedCount>
    <lineItemsKeyedPercent>0.0</lineItemsKeyedPercent>
    <keyDepartmentCount>0.0</keyDepartmentCount>
    <keyDepartmentPercent>0.0</keyDepartmentPercent>
    <IncludeTax>true</IncludeTax>
    <LineItem VoidFlag="false">
      <SequenceNumber>1</SequenceNumber>
      <Sale>
        <sequenceNumber>1</sequenceNumber>
        <ItemCode>1366</ItemCode>
        <ItemType>0</ItemType>
        <Quantity>1.0</Quantity>
        <units>0.0</units>
        <RegularSalesUnitPrice>0.0</RegularSalesUnitPrice>
        <ActualSalesUnitPrice>0.0</ActualSalesUnitPrice>
        <ExtendedAmount>174.0</ExtendedAmount>
        <unitDiscountAmount>0.0</unitDiscountAmount>
        <extendedDiscountAmount>0.0</extendedDiscountAmount>
        <EntryMethodCode>KEYED</EntryMethodCode>
        <TaxType></TaxType>
        <POSDepartment>115</POSDepartment>
        <MerchandiseHierarchyGroup>800000</MerchandiseHierarchyGroup>
        <PriceEntered>0</PriceEntered>
        <appliedTax>0.0</appliedTax>
      </Sale>
    </LineItem>
    <LineItem VoidFlag="false">
      <SequenceNumber>2</SequenceNumber>
      <Sale>
        <sequenceNumber>2</sequenceNumber>
        <ItemCode>1366</ItemCode>
        <ItemType>0</ItemType>
        <Quantity>1.0</Quantity>
        <units>0.0</units>
        <RegularSalesUnitPrice>0.0</RegularSalesUnitPrice>
        <ActualSalesUnitPrice>0.0</ActualSalesUnitPrice>
        <ExtendedAmount>174.0</ExtendedAmount>
        <unitDiscountAmount>0.0</unitDiscountAmount>
        <extendedDiscountAmount>0.0</extendedDiscountAmount>
        <EntryMethodCode>KEYED</EntryMethodCode>
        <TaxType></TaxType>
        <POSDepartment>115</POSDepartment>
        <MerchandiseHierarchyGroup>800000</MerchandiseHierarchyGroup>
        <PriceEntered>0</PriceEntered>
      </Sale>
    </LineItem>
    <LineItem VoidFlag="false">
      <SequenceNumber>3</SequenceNumber>
      <Sale>
        <sequenceNumber>3</sequenceNumber>
        <ItemCode>1366</ItemCode>
        <ItemType>0</ItemType>
        <Quantity>1.0</Quantity>
        <units>0.0</units>
        <RegularSalesUnitPrice>0.0</RegularSalesUnitPrice>
        <ActualSalesUnitPrice>0.0</ActualSalesUnitPrice>
        <ExtendedAmount>174.0</ExtendedAmount>
        <unitDiscountAmount>0.0</unitDiscountAmount>
        <extendedDiscountAmount>0.0</extendedDiscountAmount>
        <EntryMethodCode>KEYED</EntryMethodCode>
        <TaxType></TaxType>
        <POSDepartment>115</POSDepartment>
        <MerchandiseHierarchyGroup>800000</MerchandiseHierarchyGroup>
        <PriceEntered>0</PriceEntered>
      </Sale>
    </LineItem>
    <LineItem VoidFlag="false">
      <SequenceNumber>4</SequenceNumber>
      <Sale>
        <sequenceNumber>4</sequenceNumber>
        <ItemCode>1366</ItemCode>
        <ItemType>0</ItemType>
        <Quantity>1.0</Quantity>
        <units>0.0</units>
        <RegularSalesUnitPrice>0.0</RegularSalesUnitPrice>
        <ActualSalesUnitPrice>0.0</ActualSalesUnitPrice>
        <ExtendedAmount>174.0</ExtendedAmount>
        <unitDiscountAmount>0.0</unitDiscountAmount>
        <extendedDiscountAmount>0.0</extendedDiscountAmount>
        <EntryMethodCode>KEYED</EntryMethodCode>
        <TaxType></TaxType>
        <POSDepartment>115</POSDepartment>
        <MerchandiseHierarchyGroup>800000</MerchandiseHierarchyGroup>
        <PriceEntered>0</PriceEntered>
      </Sale>
    </LineItem>
    <LineItem VoidFlag="false">
      <SequenceNumber>5</SequenceNumber>
      <Sale>
        <sequenceNumber>5</sequenceNumber>
        <ItemCode>1366</ItemCode>
        <ItemType>0</ItemType>
        <Quantity>1.0</Quantity>
        <units>0.0</units>
        <RegularSalesUnitPrice>0.0</RegularSalesUnitPrice>
        <ActualSalesUnitPrice>0.0</ActualSalesUnitPrice>
        <ExtendedAmount>174.0</ExtendedAmount>
        <unitDiscountAmount>0.0</unitDiscountAmount>
        <extendedDiscountAmount>0.0</extendedDiscountAmount>
        <EntryMethodCode>KEYED</EntryMethodCode>
        <TaxType></TaxType>
        <POSDepartment>115</POSDepartment>
        <MerchandiseHierarchyGroup>800000</MerchandiseHierarchyGroup>
        <PriceEntered>0</PriceEntered>
      </Sale>
    </LineItem>
    <LineItem VoidFlag="false">
      <SequenceNumber>6</SequenceNumber>
      <Sale>
        <sequenceNumber>6</sequenceNumber>
        <ItemCode>5135</ItemCode>
        <ItemType>0</ItemType>
        <Quantity>1.0</Quantity>
        <units>0.0</units>
        <RegularSalesUnitPrice>0.0</RegularSalesUnitPrice>
        <ActualSalesUnitPrice>0.0</ActualSalesUnitPrice>
        <ExtendedAmount>118.0</ExtendedAmount>
        <unitDiscountAmount>0.0</unitDiscountAmount>
        <extendedDiscountAmount>0.0</extendedDiscountAmount>
        <EntryMethodCode>KEYED</EntryMethodCode>
        <TaxType>D</TaxType>
        <POSDepartment>22</POSDepartment>
        <MerchandiseHierarchyGroup>255000</MerchandiseHierarchyGroup>
        <PriceEntered>0</PriceEntered>
        <appliedTax>0.1764</appliedTax>
      </Sale>
    </LineItem>
    <LineItem VoidFlag="false">
      <SequenceNumber>7</SequenceNumber>
      <Sale>
        <sequenceNumber>7</sequenceNumber>
        <ItemCode>5135</ItemCode>
        <ItemType>0</ItemType>
        <Quantity>1.0</Quantity>
        <units>0.0</units>
        <RegularSalesUnitPrice>0.0</RegularSalesUnitPrice>
        <ActualSalesUnitPrice>0.0</ActualSalesUnitPrice>
        <ExtendedAmount>118.0</ExtendedAmount>
        <unitDiscountAmount>0.0</unitDiscountAmount>
        <extendedDiscountAmount>0.0</extendedDiscountAmount>
        <EntryMethodCode>KEYED</EntryMethodCode>
        <TaxType>D</TaxType>
        <POSDepartment>22</POSDepartment>
        <MerchandiseHierarchyGroup>255000</MerchandiseHierarchyGroup>
        <PriceEntered>0</PriceEntered>
        <appliedTax>0.1764</appliedTax>
      </Sale>
    </LineItem>
    <LineItem VoidFlag="false">
      <SequenceNumber>8</SequenceNumber>
      <Sale>
        <sequenceNumber>8</sequenceNumber>
        <ItemCode>5135</ItemCode>
        <ItemType>0</ItemType>
        <Quantity>1.0</Quantity>
        <units>0.0</units>
        <RegularSalesUnitPrice>0.0</RegularSalesUnitPrice>
        <ActualSalesUnitPrice>0.0</ActualSalesUnitPrice>
        <ExtendedAmount>118.0</ExtendedAmount>
        <unitDiscountAmount>0.0</unitDiscountAmount>
        <extendedDiscountAmount>0.0</extendedDiscountAmount>
        <EntryMethodCode>KEYED</EntryMethodCode>
        <TaxType>D</TaxType>
        <POSDepartment>22</POSDepartment>
        <MerchandiseHierarchyGroup>255000</MerchandiseHierarchyGroup>
        <PriceEntered>0</PriceEntered>
        <appliedTax>0.1764</appliedTax>
      </Sale>
    </LineItem>
    <LineItem VoidFlag="false">
      <SequenceNumber>9</SequenceNumber>
      <Sale>
        <sequenceNumber>9</sequenceNumber>
        <ItemCode>5135</ItemCode>
        <ItemType>0</ItemType>
        <Quantity>1.0</Quantity>
        <units>0.0</units>
        <RegularSalesUnitPrice>0.0</RegularSalesUnitPrice>
        <ActualSalesUnitPrice>0.0</ActualSalesUnitPrice>
        <ExtendedAmount>118.0</ExtendedAmount>
        <unitDiscountAmount>0.0</unitDiscountAmount>
        <extendedDiscountAmount>0.0</extendedDiscountAmount>
        <EntryMethodCode>KEYED</EntryMethodCode>
        <TaxType>D</TaxType>
        <POSDepartment>22</POSDepartment>
        <MerchandiseHierarchyGroup>255000</MerchandiseHierarchyGroup>
        <PriceEntered>0</PriceEntered>
        <appliedTax>0.0408</appliedTax>
      </Sale>
    </LineItem>
    <LineItem VoidFlag="false">
      <SequenceNumber>10</SequenceNumber>
      <Tender TenderType="11">
        <TenderAccountNumber></TenderAccountNumber>
        <ForeignCurrencyAmount>0.0</ForeignCurrencyAmount>
        <Amount>1400.0</Amount>
        <FeeAmount>0.0</FeeAmount>
        <Status>0</Status>
        <ExchangeRate>0.0</ExchangeRate>
        <amountAppliedToTransaction>0.0</amountAppliedToTransaction>
      </Tender>
    </LineItem>
    <LineItem TypeCode="1">
      <SequenceNumber>12</SequenceNumber>
      <Tax TaxType="A">
        <taxablePercent>0.0</taxablePercent>
        <TaxableAmount>472.0</TaxableAmount>
        <Amount>57.0</Amount>
        <taxPercent>0.0</taxPercent>
      </Tax>
    </LineItem>
    <Totals>
      <Total TotalType="TransactionTaxAmount" CancelFlag="false">
        <Amount>57.0</Amount>
      </Total>
      <Total TotalType="TransactionGrossPositiveAmount" CancelFlag="false">
        <Amount>1399.0</Amount>
      </Total>
      <Total TotalType="TransactionGrossNegativeAmount" CancelFlag="false">
        <Amount>0.0</Amount>
      </Total>
    </Totals>
    <InvoiceData>
      <CustomerID>1792292212001</CustomerID>
      <customerType>2</customerType>
      <CustomerName>QQ</CustomerName>
      <Address>022</Address>
      <Telephone>22</Telephone>
    </InvoiceData>
    <FacturaElec>
      <Fecha>160609</Fecha>
      <Hora>124440</Hora>
      <NumeroDoc>000001073</NumeroDoc>
      <TipoDoc>01</TipoDoc>
      <Estado>0</Estado>
      <NumeroFac>001-005-000001073</NumeroFac>
    </FacturaElec>
    <StringUsuariosDataList>
      <StringUsuario>
        <SequenceNumber>1</SequenceNumber>
        <Cadena>99&apos;|&apos;06&apos;|&apos;27&apos;|&apos;5&apos;|&apos;1792292212001&apos;|&apos;2&apos;|&apos;QQ&apos;|&apos;022&apos;|&apos;22&apos;|&apos;0&apos;|&apos;</Cadena>
      </StringUsuario>
      <StringUsuario>
        <SequenceNumber>2</SequenceNumber>
        <Cadena>99&apos;|&apos;06&apos;|&apos;41&apos;|&apos;5&apos;|&apos;15&apos;|&apos;0906201612&apos;|&apos;1366&apos;|&apos;174&apos;|&apos;.000000&apos;|&apos;174&apos;|&apos;0&apos;|&apos;0&apos;|&apos;</Cadena>
      </StringUsuario>
      <StringUsuario>
        <SequenceNumber>3</SequenceNumber>
        <Cadena>99&apos;|&apos;06&apos;|&apos;41&apos;|&apos;5&apos;|&apos;15&apos;|&apos;0906201612&apos;|&apos;1366&apos;|&apos;174&apos;|&apos;.000000&apos;|&apos;174&apos;|&apos;0&apos;|&apos;0&apos;|&apos;</Cadena>
      </StringUsuario>
      <StringUsuario>
        <SequenceNumber>4</SequenceNumber>
        <Cadena>99&apos;|&apos;06&apos;|&apos;41&apos;|&apos;5&apos;|&apos;15&apos;|&apos;0906201612&apos;|&apos;1366&apos;|&apos;174&apos;|&apos;.000000&apos;|&apos;174&apos;|&apos;0&apos;|&apos;0&apos;|&apos;</Cadena>
      </StringUsuario>
      <StringUsuario>
        <SequenceNumber>5</SequenceNumber>
        <Cadena>99&apos;|&apos;06&apos;|&apos;41&apos;|&apos;5&apos;|&apos;15&apos;|&apos;0906201612&apos;|&apos;1366&apos;|&apos;174&apos;|&apos;.000000&apos;|&apos;174&apos;|&apos;0&apos;|&apos;0&apos;|&apos;</Cadena>
      </StringUsuario>
      <StringUsuario>
        <SequenceNumber>6</SequenceNumber>
        <Cadena>99&apos;|&apos;06&apos;|&apos;41&apos;|&apos;5&apos;|&apos;15&apos;|&apos;0906201612&apos;|&apos;1366&apos;|&apos;174&apos;|&apos;.000000&apos;|&apos;174&apos;|&apos;0&apos;|&apos;0&apos;|&apos;</Cadena>
      </StringUsuario>
      <StringUsuario>
        <SequenceNumber>7</SequenceNumber>
        <Cadena>99&apos;|&apos;06&apos;|&apos;41&apos;|&apos;5&apos;|&apos;15&apos;|&apos;0906201612&apos;|&apos;5135&apos;|&apos;164&apos;|&apos;.176400&apos;|&apos;147&apos;|&apos;0&apos;|&apos;0&apos;|&apos;</Cadena>
      </StringUsuario>
      <StringUsuario>
        <SequenceNumber>8</SequenceNumber>
        <Cadena>99&apos;|&apos;06&apos;|&apos;41&apos;|&apos;5&apos;|&apos;15&apos;|&apos;0906201612&apos;|&apos;5135&apos;|&apos;164&apos;|&apos;.176400&apos;|&apos;147&apos;|&apos;0&apos;|&apos;0&apos;|&apos;</Cadena>
      </StringUsuario>
      <StringUsuario>
        <SequenceNumber>9</SequenceNumber>
        <Cadena>99&apos;|&apos;06&apos;|&apos;41&apos;|&apos;5&apos;|&apos;15&apos;|&apos;0906201612&apos;|&apos;5135&apos;|&apos;164&apos;|&apos;.176400&apos;|&apos;147&apos;|&apos;0&apos;|&apos;0&apos;|&apos;</Cadena>
      </StringUsuario>
      <StringUsuario>
        <SequenceNumber>10</SequenceNumber>
        <Cadena>99&apos;|&apos;06&apos;|&apos;41&apos;|&apos;5&apos;|&apos;15&apos;|&apos;0906201612&apos;|&apos;5135&apos;|&apos;37&apos;|&apos;.040800&apos;|&apos;88&apos;|&apos;0&apos;|&apos;0&apos;|&apos;</Cadena>
      </StringUsuario>
      <StringUsuario>
        <SequenceNumber>11</SequenceNumber>
        <Cadena>99&apos;|&apos;06&apos;|&apos;07&apos;|&apos;57&apos;|&apos;</Cadena>
      </StringUsuario>
      <StringUsuario>
        <SequenceNumber>12</SequenceNumber>
        <Cadena>99&apos;|&apos;06&apos;|&apos;23&apos;|&apos;090616&apos;|&apos;</Cadena>
      </StringUsuario>
      <StringUsuario>
        <SequenceNumber>13</SequenceNumber>
        <Cadena>99&apos;|&apos;06&apos;|&apos;20&apos;|&apos;160609&apos;|&apos;124440&apos;|&apos;000001073&apos;|&apos;01&apos;|&apos;0&apos;|&apos;001-005-000001073&apos;|&apos;</Cadena>
      </StringUsuario>
      <StringUsuario>
        <SequenceNumber>14</SequenceNumber>
        <Cadena>99&apos;|&apos;06&apos;|&apos;27&apos;|&apos;5&apos;|&apos;1792292212001&apos;|&apos;2&apos;|&apos;QQ&apos;|&apos;022&apos;|&apos;22&apos;|&apos;1&apos;|&apos;</Cadena>
      </StringUsuario>
    </StringUsuariosDataList>
  </RetailTransaction>
</Transaction>